{
  "lines": [
    {
      "id": 0,
      "text": "thenewboston.travis;",
      "vertice": {
        "x_min": 6.0,
        "y_min": 9.0,
        "x_max": 423.0,
        "y_max": 41.0
      }
    },
    {
      "id": 1,
      "text": "Splash {",
      "vertice": {
        "x_min": 33.0,
        "y_min": 79.0,
        "x_max": 208.0,
        "y_max": 138.0
      }
    },
    {
      "id": 2,
      "text": "com.thenewboston.travis.Splash",
      "vertice": {
        "x_min": 108.0,
        "y_min": 167.0,
        "x_max": 636.0,
        "y_max": 191.0
      }
    },
    {
      "id": 3,
      "text": "Press'F2'for focus",
      "vertice": {
        "x_min": 431.0,
        "y_min": 322.0,
        "x_max": 672.0,
        "y_max": 350.0
      }
    }
  ]
}