{
  "lines": [
    {
      "id": 0,
      "text": "Java Project",
      "vertice": {
        "x_min": 45.0,
        "y_min": 21.0,
        "x_max": 262.0,
        "y_max": 49.0
      }
    },
    {
      "id": 1,
      "text": "Android Project",
      "vertice": {
        "x_min": 62.0,
        "y_min": 67.0,
        "x_max": 323.0,
        "y_max": 96.0
      }
    },
    {
      "id": 2,
      "text": "Project...",
      "vertice": {
        "x_min": 43.0,
        "y_min": 114.0,
        "x_max": 220.0,
        "y_max": 144.0
      }
    },
    {
      "id": 3,
      "text": "Package",
      "vertice": {
        "x_min": 46.0,
        "y_min": 183.0,
        "x_max": 210.0,
        "y_max": 219.0
      }
    },
    {
      "id": 4,
      "text": "Class",
      "vertice": {
        "x_min": 85.0,
        "y_min": 231.0,
        "x_max": 169.0,
        "y_max": 263.0
      }
    },
    {
      "id": 5,
      "text": "Interface",
      "vertice": {
        "x_min": 49.0,
        "y_min": 278.0,
        "x_max": 218.0,
        "y_max": 308.0
      }
    },
    {
      "id": 6,
      "text": "Enum",
      "vertice": {
        "x_min": 84.0,
        "y_min": 325.0,
        "x_max": 173.0,
        "y_max": 357.0
      }
    },
    {
      "id": 7,
      "text": "Annotation",
      "vertice": {
        "x_min": 84.0,
        "y_min": 375.0,
        "x_max": 253.0,
        "y_max": 401.0
      }
    },
    {
      "id": 8,
      "text": "Source Folder",
      "vertice": {
        "x_min": 48.0,
        "y_min": 419.0,
        "x_max": 295.0,
        "y_max": 448.0
      }
    },
    {
      "id": 9,
      "text": "Java Working Set",
      "vertice": {
        "x_min": 51.0,
        "y_min": 467.0,
        "x_max": 337.0,
        "y_max": 496.0
      }
    },
    {
      "id": 10,
      "text": "Folder",
      "vertice": {
        "x_min": 63.0,
        "y_min": 512.0,
        "x_max": 185.0,
        "y_max": 543.0
      }
    }
  ]
}